Workbook
Name Aporte: APP!$C$19
Name patrimonio: APP!$C$22
Name qtd_anos: APP!$C$20
Name Rendimento_carteira: APP!$C$15
Name salario: APP!$C$14
Name sugestao_investimento: APP!$C$16
Name taxa_mensal: APP!$C$21

Sheet APP
B13: CONFIGURAÇÕES
B14: Salário | C14: 2000
B15: Rendimento Carteira | C15: 0.01
B16: Sugestão de aporte mensal (30%) | C16: =salario*30% -> 600
B18: INVESTIMENTO MENSAL
B19: Quanto investir por mês? | C19: 200
B20: Por quanto tempo? | C20: 10
B21: Taxa de Rendimento mensal? | C21: 0.01079
B22: Patrimônio acumulado? | C22: =FV(taxa_mensal,qtd_anos*12,Aporte*-1) -> 48656.843
B23: Dividendos mensais? | C23: =patrimonio*Rendimento_carteira -> 486.56843
B25: CENÁRIOS | C25: RENDIMENTO | D25: DIVIDENDO
A26: 2 | B26: Quanto em 2 anos? | C26: =FV($C$21,$A26*12,$C$19*-1) -> 5445.5255 | D26: =C26*Rendimento_carteira -> 54.455255
A27: 5 | B27: Quanto em 5 anos? | C27: =FV($C$21,$A27*12,$C$19*-1) -> 16755.383 | D27: =C27*Rendimento_carteira -> 167.55383
A28: 10 | B28: Quanto em 10 anos? | C28: =FV($C$21,$A28*12,$C$19*-1) -> 48656.843 | D28: =C28*Rendimento_carteira -> 486.56843
A29: 20 | B29: Quanto em 20 anos? | C29: =FV($C$21,$A29*12,$C$19*-1) -> 225039.68 | D29: =C29*Rendimento_carteira -> 2250.3968
A30: 30 | B30: Quanto em 30 anos? | C30: =FV($C$21,$A30*12,$C$19*-1) -> 864433.93 | D30: =C30*Rendimento_carteira -> 8644.3393
B33: PERFIL | C33: MODERADO
B34: VALOR DE APORTE MENSAL | C34: =Aporte -> 200
B36: TIPO DE FII | C36: Percentual Sugerido | D36: Valores
B37: PAPEL | C37: =VLOOKUP($C$33&"-"&B37,'Tabela auxiliar'!A2:D20,4,FALSE) -> 0.32 | D37: =C37*$C$34 -> 64
B38: TIJOLO | C38: =VLOOKUP($C$33&"-"&B38,'Tabela auxiliar'!A3:D21,4,FALSE) -> 0.35 | D38: =C38*$C$34 -> 70
B39: HÍBRIDOS | C39: =VLOOKUP($C$33&"-"&B39,'Tabela auxiliar'!A4:D22,4,FALSE) -> 0.08 | D39: =C39*$C$34 -> 16
B40: FOF's | C40: =VLOOKUP($C$33&"-"&B40,'Tabela auxiliar'!A5:D23,4,FALSE) -> 0.1 | D40: =C40*$C$34 -> 20
B41: DESENVOLVIMENTO | C41: =VLOOKUP($C$33&"-"&B41,'Tabela auxiliar'!A6:D24,4,FALSE) -> 0.1 | D41: =C41*$C$34 -> 20
B42: HOTELARIAS | C42: =VLOOKUP($C$33&"-"&B42,'Tabela auxiliar'!A7:D25,4,FALSE) -> 0.1 | D42: =C42*$C$34 -> 20
D43: =SUM(D37:D42) -> 210

Sheet APP_1
B13: CONFIGURAÇÕES | F13: INVESTIMENTO MENSAL
B14: Salário | C14: 2000 | F14: Quanto investir por mês? | G14: 200
B15: Rendimento Carteira | C15: 0.01 | F15: Por quanto tempo? | G15: 10
B16: Sugestão de aporte mensal (30%) | C16: =salario*30% -> 600 | F16: Taxa de Rendimento mensal? | G16: 0.01079
F17: Patrimônio acumulado? | G17: =FV(taxa_mensal,qtd_anos*12,Aporte*-1) -> 48656.843
B18: PERFIL DE INVESTIDOR | C18: MODERADO | F18: Dividendos mensais? | G18: =patrimonio*Rendimento_carteira -> 486.56843
B19: VALOR DE APORTE MENSAL | C19: =Aporte -> 200
F20: CENÁRIOS | G20: RENDIMENTO | H20: DIVIDENDO
F21: Quanto em 2 anos? | G21: =FV($G$16,$A26*12,$G$14*-1) -> 5445.5255 | H21: =G21*Rendimento_carteira -> 54.455255
F22: Quanto em 5 anos? | G22: =FV($G$16,$A27*12,$G$14*-1) -> 16755.383 | H22: =G22*Rendimento_carteira -> 167.55383
F23: Quanto em 10 anos? | G23: =FV($G$16,$A28*12,$G$14*-1) -> 48656.843 | H23: =G23*Rendimento_carteira -> 486.56843
F24: Quanto em 20 anos? | G24: =FV($G$16,$A29*12,$G$14*-1) -> 225039.68 | H24: =G24*Rendimento_carteira -> 2250.3968
F25: Quanto em 30 anos? | G25: =FV($G$16,$A30*12,$G$14*-1) -> 864433.93 | H25: =G25*Rendimento_carteira -> 8644.3393
A26: 2
A27: 5 | F27: TIPO DE FII | G27: Percentual Sugerido | H27: Valores
A28: 10 | F28: PAPEL | G28: =VLOOKUP($C$18&"-"&F28,'Tabela auxiliar'!A2:D20,4,FALSE) -> 0.32 | H28: =G28*$C$19 -> 64
A29: 20 | F29: TIJOLO | G29: =VLOOKUP($C$18&"-"&F29,'Tabela auxiliar'!A3:D21,4,FALSE) -> 0.35 | H29: =G29*$C$19 -> 70
A30: 30 | F30: HÍBRIDOS | G30: =VLOOKUP($C$18&"-"&F30,'Tabela auxiliar'!A4:D22,4,FALSE) -> 0.08 | H30: =G30*$C$19 -> 16
F31: FOF's | G31: =VLOOKUP($C$18&"-"&F31,'Tabela auxiliar'!A5:D23,4,FALSE) -> 0.1 | H31: =G31*$C$19 -> 20
F32: DESENVOLVIMENTO | G32: =VLOOKUP($C$18&"-"&F32,'Tabela auxiliar'!A6:D24,4,FALSE) -> 0.1 | H32: =G32*$C$19 -> 20
F33: HOTELARIAS | G33: =VLOOKUP($C$18&"-"&F33,'Tabela auxiliar'!A7:D25,4,FALSE) -> 0.1 | H33: =G33*$C$19 -> 20
H34: =SUM(H28:H33) -> 210

Sheet Tabela auxiliar
A2: CHAVE | B2: PERFIL | C2: TIPO DE FII | D2: %
A3: =B3&"-"&C3 -> CONSERVADOR-PAPEL | B3: CONSERVADOR | C3: PAPEL | D3: 0.3
A4: =B4&"-"&C4 -> CONSERVADOR-TIJOLO | B4: CONSERVADOR | C4: TIJOLO | D4: 0.5
A5: =B5&"-"&C5 -> CONSERVADOR-HÍBRIDOS | B5: CONSERVADOR | C5: HÍBRIDOS | D5: 0.1
A6: =B6&"-"&C6 -> CONSERVADOR-FOF's | B6: CONSERVADOR | C6: FOF's | D6: 0.1
A7: =B7&"-"&C7 -> CONSERVADOR-DESENVOLVIMENTO | B7: CONSERVADOR | C7: DESENVOLVIMENTO | D7: 0
A8: =B8&"-"&C8 -> CONSERVADOR-HOTELARIAS | B8: CONSERVADOR | C8: HOTELARIAS | D8: 0
A9: =B9&"-"&C9 -> MODERADO-PAPEL | B9: MODERADO | C9: PAPEL | D9: 0.32
A10: =B10&"-"&C10 -> MODERADO-TIJOLO | B10: MODERADO | C10: TIJOLO | D10: 0.35
A11: =B11&"-"&C11 -> MODERADO-HÍBRIDOS | B11: MODERADO | C11: HÍBRIDOS | D11: 0.08
A12: =B12&"-"&C12 -> MODERADO-FOF's | B12: MODERADO | C12: FOF's | D12: 0.1
A13: =B13&"-"&C13 -> MODERADO-DESENVOLVIMENTO | B13: MODERADO | C13: DESENVOLVIMENTO | D13: 0.1
A14: =B14&"-"&C14 -> MODERADO-HOTELARIAS | B14: MODERADO | C14: HOTELARIAS | D14: 0.1
... A20: =B20&"-"&C20 -> AGRESSIVO-HOTELARIAS | B20: AGRESSIVO | C20: HOTELARIAS | D20: 0.1
